{
  "n2-l20-g02": {
    "level": "N2",
    "lesson": 20,
    "pattern": "〜きり",
    "body": "意味： ⇒ 〜という動作の後、そのままずっと同じ状態が続く。\n① その本は、子供のころ読んだきり、その後一度も読んでいない。\n② 父は朝、出かけたきりなんです。まだ戻ってきていません。\n③ 日本は長寿国だが、寝たきりの老人の数も多い。\n④ 彼に最後に会ったのは卒業式の時です。それきり、一度も会っていません。\n接续： 動 た形 + きり\n注意： 後には、次に予想されることが起きていない状態を表す文が来る。否定文が多い。④の「それきり」は慣用的な言い方。",
    "questions": [
      {
        "q": "1",
        "stem": "この果物は（　）きり、ずっと食べていない。",
        "opts": [
          [
            "a",
            "国を出るとき食べた"
          ],
          [
            "b",
            "国では毎日食べた"
          ],
          [
            "c",
            "国では手に入らなかった"
          ]
        ]
      },
      {
        "q": "2",
        "stem": "新しい本を買ったきり、（　）。",
        "opts": [
          [
            "a",
            "汚してしまった"
          ],
          [
            "b",
            "2回しか読んでいない"
          ],
          [
            "c",
            "ページを開いてもいない"
          ]
        ]
      },
      {
        "q": "3",
        "stem": "友達にお金を貸したきり、（　）。",
        "opts": [
          [
            "a",
            "やっと返してもらった"
          ],
          [
            "b",
            "返してもらっていない"
          ],
          [
            "c",
            "あした返すと言っている"
          ]
        ]
      }
    ]
  },
  "n2-l20-g03": {
    "level": "N2",
    "lesson": 20,
    "pattern": "〜あげく",
    "body": "意味： ⇒ いろいろ〜した後で、結局残念な結果になった。\n① 5時間に及ぶ議論のあげく、結局、結論が出なかった。\n② いろいろ文句を言ったあげく、その客は何も買わずに帰った。\n③ さんざん悩んだあげく、国へ帰ることにした。\n接续： 名-の・動 た形 + あげく\n注意： 大変な状態が続いたという意味の文につく。後には、いい結果を表す文はあまり来ない。",
    "questions": [
      {
        "q": "1",
        "stem": "彼は（　）あげく、弁護士になるのをあきらめてしまった。",
        "opts": [
          [
            "a",
            "試験に落ちた"
          ],
          [
            "b",
            "妻と相談した"
          ],
          [
            "c",
            "10年も勉強を続けた"
          ]
        ]
      },
      {
        "q": "2",
        "stem": "さんざん人に迷惑をかけたあげく、（　）。",
        "opts": [
          [
            "a",
            "彼は成功した"
          ],
          [
            "b",
            "彼の姿が見えない"
          ],
          [
            "c",
            "彼はいなくなってしまった"
          ]
        ]
      },
      {
        "q": "3",
        "stem": "わたしは（　）あげく、再婚はしないことにした。",
        "opts": [
          [
            "a",
            "迷った"
          ],
          [
            "b",
            "離婚した"
          ],
          [
            "c",
            "彼と出会った"
          ]
        ]
      }
    ]
  },
  "n2-l20-g04": {
    "level": "N2",
    "lesson": 20,
    "pattern": "〜末（に）",
    "body": "意味： ⇒ いろいろ〜した後で、最終的にある結果になった。\n① 数回におよぶ議論の末、Aの案を採用することにした。\n② 長い戦いの末、ついに勝利を勝ち取った。\n③ 悩んだ末に、手術を受けようと決めた。\n接续： 名-の・動 た形 + 末（に）\n注意： 大変な状態が続いたという意味の文につく。後には、結末や決断を表す文が来る。",
    "questions": [
      {
        "q": "1",
        "stem": "（　）末に、やっと今の会社に落ち着いた。",
        "opts": [
          [
            "a",
            "退職した"
          ],
          [
            "b",
            "転職を繰り返した"
          ],
          [
            "c",
            "就職した"
          ]
        ]
      },
      {
        "q": "2",
        "stem": "（　）末に、チベットに行くことにした。",
        "opts": [
          [
            "a",
            "その本を読んだ"
          ],
          [
            "b",
            "あれこれ考えた"
          ],
          [
            "c",
            "チベットの映画を見た"
          ]
        ]
      },
      {
        "q": "3",
        "stem": "あちこち面接を受けた末に、（　）。",
        "opts": [
          [
            "a",
            "やっとこの会社に合格した"
          ],
          [
            "b",
            "あの会社にどうしても入りたい"
          ],
          [
            "c",
            "まだ就職が決まっていない"
          ]
        ]
      },
      {
        "q": "4",
        "stem": "両親や先生とも話し合った末に、（　）。",
        "opts": [
          [
            "a",
            "留学したい"
          ],
          [
            "b",
            "来年留学する"
          ],
          [
            "c",
            "留学することに決めた"
          ]
        ]
      }
    ]
  },
  "n2-l20-g05": {
    "level": "N2",
    "lesson": 20,
    "pattern": "〜ところだった",
    "body": "意味： ⇒ 〜という状況になる一歩手前だったが、実際にはそうならなかった。\n① あ、今日は15日か。うっかり約束を忘れるところだった。\n② 気をつけてくださいよ。気がつくのが遅かったら火事になるところでしたよ。\n③ 朝寝坊して、危うく試験が受けられないところだった。\n④ ああ、残念だ。もう少しで100点取れるところだったのに、97点だった。\n接续： 動 辞書形／ない形 + ところだった\n注意： 「うっかり・危うく」などの副詞と一緒に使って、悪い状況になりそうだったことを表す文が多いが、④のように「〜のに」を使って、いい状況の一歩手前だったことを表す文もある。自然現象など、（注意しても）避けられない事情を言う文には使いにくい。",
    "questions": [
      {
        "q": "1",
        "stem": "あの時は危なかった。もう少しで（　）ところだった。",
        "opts": [
          [
            "a",
            "死ぬ"
          ],
          [
            "b",
            "死んだ"
          ],
          [
            "c",
            "死にそうな"
          ]
        ]
      },
      {
        "q": "2",
        "stem": "ぼんやりと歩いていて、（　）ところだった。",
        "opts": [
          [
            "a",
            "車にぶつかる"
          ],
          [
            "b",
            "駅に着く"
          ],
          [
            "c",
            "昔のことを思い出す"
          ]
        ]
      },
      {
        "q": "3",
        "stem": "危うく予定の電車に乗り遅れるところだったが、（　）。",
        "opts": [
          [
            "a",
            "タクシーで行った"
          ],
          [
            "b",
            "なんとか間に合った"
          ],
          [
            "c",
            "やはり遅れた"
          ]
        ]
      },
      {
        "q": "4",
        "stem": "ああ、よかった。もう少しで（　）ところだった。",
        "opts": [
          [
            "a",
            "雨が降る"
          ],
          [
            "b",
            "台風が来る"
          ],
          [
            "c",
            "携帯電話を忘れる"
          ]
        ]
      }
    ]
  },
  "n2-l20-g06": {
    "level": "N2",
    "lesson": 20,
    "pattern": "〜ずじまいだ",
    "body": "意味： ⇒ 〜ようと思っていたのに、結局できなかった・〜ないで終わった。\n① いろんな人に聞いてみたが、結局田中さんの連絡先はわからずじまいだった。\n② 彼女にラブレターを書いたけれど、勇気がなくて出せずじまいだった。\n③ 留学中に旅行したかったが、忙しくてどこへも行かずじまいで帰国した。\n接续： 動 ない + ずじまいだ\n注意： 全体として、時期を逃してしまったという残念な気持ちを表す。過去形の文が多い。まだチャンスがある場合には使わない。",
    "questions": [
      {
        "q": "1",
        "stem": "あの映画は（　）、忙しくて見ずじまいだった。",
        "opts": [
          [
            "a",
            "見たかったが"
          ],
          [
            "b",
            "見ようと思っているが"
          ],
          [
            "c",
            "まだ公開しているが"
          ]
        ]
      },
      {
        "q": "2",
        "stem": "マレーシアに行ったらリーさんに会おうと思っていたが、会わずじまいで（　）。",
        "opts": [
          [
            "a",
            "来週会うことになった"
          ],
          [
            "b",
            "帰国した"
          ],
          [
            "c",
            "なかなか帰国できなかった"
          ]
        ]
      },
      {
        "q": "3",
        "stem": "（　）、結局買わずじまいだった。",
        "opts": [
          [
            "a",
            "洋服屋を見て回ったが"
          ],
          [
            "b",
            "辞書が必要なのだが"
          ],
          [
            "c",
            "扇風機が安くなっているが"
          ]
        ]
      }
    ]
  },
  "n2-l21-g01": {
    "level": "N2",
    "lesson": 21,
    "pattern": "〜ぐらい・〜くらい",
    "body": "意味： ⇒ 〜は程度が軽い・最低限の程度だ。\n① うちに帰ってきたら、自分の靴ぐらいちゃんと並べなさい。\n② この携帯電話は、ちょっとぐらいならぬれても大丈夫です。\n③ 少し話したくらいで、その人がどんな人かはわからないだろう。\n接续： 名・動・形 普通形（ナ形だ→な）＋ぐらい・くらい\n注意： 说明：接在说话人认为程度轻的词语后。前接名词时，多使用「ぐらい」。",
    "questions": [
      {
        "q": "1",
        "stem": "100メートル走ったくらいで（　）なんて、運動不足だ。",
        "opts": [
          [
            "a",
            "疲れてしまった"
          ],
          [
            "b",
            "まだ走れる"
          ],
          [
            "c",
            "もっと走ろう"
          ]
        ]
      },
      {
        "q": "2",
        "stem": "メールの返事を1件書くくらい（　）。",
        "opts": [
          [
            "a",
            "大変ですよ"
          ],
          [
            "b",
            "簡単でしょう"
          ],
          [
            "c",
            "1時間かかりました"
          ]
        ]
      },
      {
        "q": "3",
        "stem": "わたしは（　）くらいで薬は飲まない。",
        "opts": [
          [
            "a",
            "風邪を引いた"
          ],
          [
            "b",
            "病気になった"
          ],
          [
            "c",
            "熱がない"
          ]
        ]
      }
    ]
  },
  "n2-l21-g02": {
    "level": "N2",
    "lesson": 21,
    "pattern": "〜など・〜なんか・〜なんて",
    "body": "意味： ⇒ 〜は価値が低い・大切ではない。「〜なんか・〜なんて」→話し言葉。\n译：……价值低，或不重要。「〜なんか・〜なんて」为口语体。\n① あの人の言ったことなど気にすることはありません。\n② 新聞記者になんかならなければよかった。仕事がきつすぎる。\n③ 桜井さんは文章がとてもうまい。わたしなんて簡単な文もちゃんと書けないのに。\n接续： 名（＋助詞）＋など・なんか・なんて\n注意： 说明：接在说话人认为价值低的词语后。「〜なんか・〜なんて」是较随便的说法。",
    "questions": [
      {
        "q": "1",
        "stem": "お金など（　）と思っていた時もあった。",
        "opts": [
          [
            "a",
            "たくさん欲しい"
          ],
          [
            "b",
            "必要ない"
          ],
          [
            "c",
            "どんどんなくなってしまう"
          ]
        ]
      },
      {
        "q": "2",
        "stem": "カップラーメンなんか（　）。",
        "opts": [
          [
            "a",
            "毎日は食べたくない"
          ],
          [
            "b",
            "安くて便利でいい"
          ],
          [
            "c",
            "わたしは好きだ"
          ]
        ]
      },
      {
        "q": "3",
        "stem": "漫画なんて（　）。",
        "opts": [
          [
            "a",
            "大切にとっておけ"
          ],
          [
            "b",
            "たくさん読んでみろ"
          ],
          [
            "c",
            "捨ててしまえ"
          ]
        ]
      }
    ]
  },
  "n2-l21-g03": {
    "level": "N2",
    "lesson": 21,
    "pattern": "〜まで・〜までして・〜てまで",
    "body": "意味： ⇒ 〜という極端な程度のもの・ことも、ある状態だ・あることをする。\n① 一番に賛成してくれると思っていた母までわたしの結婚に反対した。\n② カンニングまでしていい点を取りたかったのですか。\n③ 遊園地では、みんな長い時間並んでまでジェットコースターに乗りたがる。\n④ 家族や友人を悲しませるようなことをしてまで成功したいとは思わない。\n接续： 名（＋助詞）＋まで・までして／動て形＋まで\n注意： 说明：接在表示极端、含有意外性的事例的词语后。「〜までして・〜てまで」表示令人惊讶或气愤的手段、事态，整体表达责难、疑问、惊讶等心情。",
    "questions": [
      {
        "q": "1",
        "stem": "（　）までそのコンサートを見に行きたかったんですか。",
        "opts": [
          [
            "a",
            "親にうそをついて"
          ],
          [
            "b",
            "親に止められて"
          ],
          [
            "c",
            "親と相談して"
          ]
        ]
      },
      {
        "q": "2",
        "stem": "昨日のマラソン大会には、（　）まで参加した。",
        "opts": [
          [
            "a",
            "若い女性"
          ],
          [
            "b",
            "高校生"
          ],
          [
            "c",
            "90歳のお年寄り"
          ]
        ]
      },
      {
        "q": "3",
        "stem": "うちの母は料理好きで、（　）まで自分で作る。",
        "opts": [
          [
            "a",
            "晩ご飯"
          ],
          [
            "b",
            "豆腐"
          ],
          [
            "c",
            "サラダ"
          ]
        ]
      },
      {
        "q": "4",
        "stem": "お金を借りてまで車を（　）。",
        "opts": [
          [
            "a",
            "買う必要はない"
          ],
          [
            "b",
            "買いたい"
          ],
          [
            "c",
            "買わなかった"
          ]
        ]
      }
    ]
  },
  "n2-l21-g04": {
    "level": "N2",
    "lesson": 21,
    "pattern": "〜として〜ない",
    "body": "意味： ⇒ あることを「最低限度の〜も全くない」と否定する。\n① 彼の提案にだれ一人として反対できなかった。\n② 人生に無駄なものは何一つとしてない。失敗も必ず何かの役に立つはずだ。\n③ 彼女はこれまで一度として練習を休んだことはない。\n接续： （何・だれ＋）一＋助数詞＋として〜ない",
    "questions": [
      {
        "q": "1",
        "stem": "今まで（　）としてあの人のことを思い出さない日はなかった。",
        "opts": [
          [
            "a",
            "1日"
          ],
          [
            "b",
            "1週間"
          ],
          [
            "c",
            "1か月"
          ]
        ]
      },
      {
        "q": "2",
        "stem": "今までの人生には何一つとして（　）。",
        "opts": [
          [
            "a",
            "楽しいことばかりだった"
          ],
          [
            "b",
            "つらいことはなかった"
          ],
          [
            "c",
            "いい思い出がある"
          ]
        ]
      },
      {
        "q": "3",
        "stem": "わたしは今まで何回も彼と試合をしているが、1回として（　）。",
        "opts": [
          [
            "a",
            "負けた"
          ],
          [
            "b",
            "勝った"
          ],
          [
            "c",
            "勝ったことはない"
          ]
        ]
      }
    ]
  },
  "n2-l21-g05": {
    "level": "N2",
    "lesson": 21,
    "pattern": "〜さえ",
    "body": "A ⇒ 〜のような極端な例もそうだから、ほかのことはもちろんだ。\n① 日本に来たばかりのときは、ひらがなさえ読めなかった。\n② 仕事がとても忙しいときは、会社に泊まることさえある。\n③ この料理は簡単だ。料理の苦手なわたしでさえ失敗しなかった。\n接续： 名（＋助詞）＋さえ\n注意： 说明：接在表示程度极端且有意外性的事例的词语后。后面不接表示说话人意志的句子，也不接要求听话人做某事的句子。③的「でさえ」是「であっても」的意思，用于主格助词「が」所能表示的场合等。\nB ⇒ 〜という一つの条件が満たされれば、ほかのことは問題にならない。\n④ 自分さえ良ければ、ほかの人のことはどうでもいいのか。\n⑤ 雨さえ降らなければ、ハイキングに出かけられますね。\n⑥ 年をとっても体さえ丈夫なら、ほかに望むことはない。\n接续： 名（＋助詞）＋さえ\n注意： 说明：以「〜さえ〜ば・〜さえ〜なら・〜さえ〜たら」的形式表示所需的最低条件。",
    "questions": [
      {
        "q": "1",
        "stem": "こんな簡単な機械は、（　）でさえ使える。",
        "opts": [
          [
            "a",
            "子供"
          ],
          [
            "b",
            "プロ"
          ],
          [
            "c",
            "大人"
          ]
        ]
      },
      {
        "q": "2",
        "stem": "自分のことさえ自分でやれば、（　）。",
        "opts": [
          [
            "a",
            "とてもいいことだよ"
          ],
          [
            "b",
            "あまりいいことではないよ"
          ],
          [
            "c",
            "何でも好きなことをしていいよ"
          ]
        ]
      },
      {
        "q": "3",
        "stem": "お金さえあれば、（　）。",
        "opts": [
          [
            "a",
            "できないこともある"
          ],
          [
            "b",
            "何でもできるのか"
          ],
          [
            "c",
            "何もできないのか"
          ]
        ]
      },
      {
        "q": "4",
        "stem": "あなたさえOKなら、（　）。",
        "opts": [
          [
            "a",
            "この案は決まります"
          ],
          [
            "b",
            "この案は決まりません"
          ],
          [
            "c",
            "わたしはOKしません"
          ]
        ]
      }
    ]
  },
  "n2-l21-g06": {
    "level": "N2",
    "lesson": 21,
    "pattern": "〜てでも",
    "body": "意味： ⇒ 普通はしないような〜という手段を使う覚悟で、あることをする。\n① 娘が家に帰りたくないと言ったら、引っ張ってでも連れて帰ろう。\n② 熱があるが、大切な約束があるので、どんなことをしてでも行かなければならない。\n③ 2倍の金額を払ってでもそのコンサートのチケットが欲しい。\n接续： 動て形＋でも",
    "questions": [
      {
        "q": "1",
        "stem": "（　）でも医師の資格を取りたい。",
        "opts": [
          [
            "a",
            "10年間勉強して"
          ],
          [
            "b",
            "これからも勉強を続けて"
          ],
          [
            "c",
            "一生懸命勉強して"
          ]
        ]
      },
      {
        "q": "2",
        "stem": "（　）でもあしたのサッカーの試合は見るつもりだ。",
        "opts": [
          [
            "a",
            "仕事をしなくて"
          ],
          [
            "b",
            "仕事を休んで"
          ],
          [
            "c",
            "テレビの前に座って"
          ]
        ]
      },
      {
        "q": "3",
        "stem": "（　）でもお金をもうけたいと言う人がいる。",
        "opts": [
          [
            "a",
            "他人より頑張って"
          ],
          [
            "b",
            "他人に協力してもらって"
          ],
          [
            "c",
            "汚い手段を使って"
          ]
        ]
      },
      {
        "q": "4",
        "stem": "病気ではないとうそをついてでも母を（　）。",
        "opts": [
          [
            "a",
            "安心させた"
          ],
          [
            "b",
            "安心させたい"
          ],
          [
            "c",
            "安心させている"
          ]
        ]
      }
    ]
  },
  "n2-l22-g01": {
    "level": "N2",
    "lesson": 22,
    "pattern": "〜とみえる",
    "body": "意味： ⇒ ある根拠があって、〜らしい・〜ようだと思う。\n① 朝からパチンコに行くなんて、ずいぶん暇だとみえる。\n② あまり食べないところを見ると、うちの猫はこのえさは好きではないとみえる。\n③ 欲しい物はなかったとみえて、客は何も買わずにすぐ店を出てしまった。\n接续： 普通形＋とみえる",
    "questions": [
      {
        "q": "1",
        "stem": "（　）風邪を引いたとみえて、せきをしていた。",
        "opts": [
          [
            "a",
            "わたしは"
          ],
          [
            "b",
            "山口さんは"
          ],
          [
            "c",
            "あなたは"
          ]
        ]
      },
      {
        "q": "2",
        "stem": "夜中に雨が降ったとみえて、（　）。",
        "opts": [
          [
            "a",
            "道路がぬれている"
          ],
          [
            "b",
            "今日はいい天気だ"
          ],
          [
            "c",
            "天気予報でそう言った"
          ]
        ]
      },
      {
        "q": "3",
        "stem": "木村さんは朝から機嫌がいい。（　）とみえる。",
        "opts": [
          [
            "a",
            "何だか楽しそう"
          ],
          [
            "b",
            "にこにこしている"
          ],
          [
            "c",
            "何かいいことがあった"
          ]
        ]
      }
    ]
  },
  "n2-l22-g02": {
    "level": "N2",
    "lesson": 22,
    "pattern": "〜かねない",
    "body": "意味： ⇒ 〜という悪い結果になる可能性がある。\n① 大事なことはみんなに相談しないと、後で文句を言われかねませんよ。\n② インターネット上では特に個人情報に注意していないと、悪用されかねない。\n③ うわさはどんどん変な方向へ発展していきかねない。\n接续： 動ます形＋かねない\n注意： 说明：用于表示从现在的状态考虑，可能会产生负面结果。比「〜おそれがある」原因更明确。",
    "questions": [
      {
        "q": "1",
        "stem": "正しい表現を使わなければ、間違った意味を（　）かねない。",
        "opts": [
          [
            "a",
            "伝える"
          ],
          [
            "b",
            "伝え"
          ],
          [
            "c",
            "伝えて"
          ]
        ]
      },
      {
        "q": "2",
        "stem": "こんなに買い物ばかりしていたら、給料日までにお金が（　）。",
        "opts": [
          [
            "a",
            "なくなりかねない"
          ],
          [
            "b",
            "少しだけありかねない"
          ],
          [
            "c",
            "足りかねない"
          ]
        ]
      },
      {
        "q": "3",
        "stem": "こんなところにかばんを置いておいたら、だれかに（　）。",
        "opts": [
          [
            "a",
            "とられかねる"
          ],
          [
            "b",
            "とられかねない"
          ],
          [
            "c",
            "とられかねられない"
          ]
        ]
      },
      {
        "q": "4",
        "stem": "音楽を聞きながら仕事をすると（　）。",
        "opts": [
          [
            "a",
            "気分が明るくなりかねない"
          ],
          [
            "b",
            "仕事がどんどん進みかねない"
          ],
          [
            "c",
            "眠くなりかねない"
          ]
        ]
      }
    ]
  },
  "n2-l22-g03": {
    "level": "N2",
    "lesson": 22,
    "pattern": "〜おそれがある",
    "body": "意味： ⇒ 〜という悪いことが起こる可能性がある。〔硬い言い方〕\n① 今夜から明日にかけて東日本で大雨のおそれがあります。\n② 「レッドデータブック」には、絶滅のおそれがある動植物について書かれている。\n③ 機械で読み取れないおそれがあるので、郵便番号ははっきり書いてください。\n④ 今後インフルエンザが広い範囲に広がるおそれはないだろう。\n接续： 名の・動辞書形/ない形＋おそれがある",
    "questions": [
      {
        "q": "1",
        "stem": "梅雨の間に雨が十分降らなければ、夏に水不足に（　）おそれがある。",
        "opts": [
          [
            "a",
            "なりそうな"
          ],
          [
            "b",
            "なる"
          ],
          [
            "c",
            "なるかもしれない"
          ]
        ]
      },
      {
        "q": "2",
        "stem": "この病気は魚に特有のもので、人が食べても（　）おそれはありません。",
        "opts": [
          [
            "a",
            "うつる"
          ],
          [
            "b",
            "うつらない"
          ],
          [
            "c",
            "体に悪い"
          ]
        ]
      },
      {
        "q": "3",
        "stem": "歯を抜いた後（　）おそれがあります。",
        "opts": [
          [
            "a",
            "食欲がない"
          ],
          [
            "b",
            "熱が高い"
          ],
          [
            "c",
            "熱が出る"
          ]
        ]
      },
      {
        "q": "4",
        "stem": "こんなに人が大勢いる所では子供が（　）おそれがある。",
        "opts": [
          [
            "a",
            "迷子になる"
          ],
          [
            "b",
            "お父さんと遊んでいる"
          ],
          [
            "c",
            "大喜びする"
          ]
        ]
      }
    ]
  },
  "n2-l22-g04": {
    "level": "N2",
    "lesson": 22,
    "pattern": "〜まい／〜ではあるまいか（→24課-5）",
    "body": "意味： ⇒ 〜ないだろう／〜ではないだろうか。〔書き言葉〕\n① 何度も計算し直したのだから、間違いはあるまい。\n② だれも信じてくれまいが、これは本当の話だ。\n③ あの子はまだ小さいから、一人で行かせては迷子になるまいかと心配だ。\n④ 田んぼに住む生物が減ったのは、農薬の使いすぎが原因ではあるまいか。\n⑤ こんなやり方では大勢の人の協力を得るのは無理なのではあるまいか。\n⑥ このまま何もしないでいたら、いつまでも問題は解決しないのではあるまいか。\n接续： 動辞書形・イ形くある・ナ形/名ではある＋まい／普通形＋のではあるまいか（ナ形・名：〜なのではあるまいか）\n注意： 说明：不用于礼貌形、过去形。通常第一人称不作主语。「〜ではあるまいか」是以问句形式委婉表达说话人的推测或意见。",
    "questions": [
      {
        "q": "1",
        "stem": "たばこはもう（　）と決心したが、やっぱりやめられない。 a 吸うまい　b 吸おうまい　c 吸わないよう",
        "opts": []
      },
      {
        "q": "2",
        "stem": "もうこんな危ないことは（　）まいと心に決めた。 a できる　b ある　c する",
        "opts": []
      },
      {
        "q": "3",
        "stem": "親に本当のことを言おうか言うまいか（　）。 a わからない　b 3日も考えている　c 関係ない",
        "opts": []
      },
      {
        "q": "4",
        "stem": "彼は勉強への興味を失ったので、（　）。 a 退学しようかするまいか　b 退学しようかと考えている　c 退学しまいかと迷っている",
        "opts": []
      }
    ]
  },
  "n2-l22-g05": {
    "level": "N2",
    "lesson": 22,
    "pattern": "〜に違いない・〜に相違ない",
    "body": "意味： ⇒ ある根拠があり、きっと〜だろうと確信を持って思う。「〜に相違ない」＝硬い言い方。\n译：有根据并确信一定是……。「〜に相違ない」为书面语。\n① 彼女はおしゃれだから、パーティーにはきっとすてきな服を着てくるに違いない。\n② 日本に1年住んでいるのだから、彼も少しは生活に慣れたに違いない。\n③ そんな山の中に住んでいて車もなかったら、生活が不便に違いない。\n④ 彼があれだけ強く主張するのは、何かはっきりした証拠があるからに相違ない。\n接续： 普通形（ナ形・名：〜である）＋に違いない・に相違ない\n注意： 说明：也有如例④那样前接「普通形＋から」的例子。",
    "questions": [
      {
        "q": "1",
        "stem": "えみさんは今日なんだか元気がない。何かあった（　）。",
        "opts": [
          [
            "a",
            "に間違いない"
          ],
          [
            "b",
            "に違いはない"
          ],
          [
            "c",
            "に違いない"
          ]
        ]
      },
      {
        "q": "2",
        "stem": "税金問題に関心が高まっているため、今回の投票率は（　）に相違ない。",
        "opts": [
          [
            "a",
            "高くなる"
          ],
          [
            "b",
            "高くなるだろう"
          ],
          [
            "c",
            "高くなりそう"
          ]
        ]
      },
      {
        "q": "3",
        "stem": "これは（　）に相違ない。",
        "opts": [
          [
            "a",
            "甘くておいしいりんご"
          ],
          [
            "b",
            "環境保護のための有効な手段"
          ],
          [
            "c",
            "お母さんが作ってくれたお弁当"
          ]
        ]
      }
    ]
  },
  "n2-l22-g06": {
    "level": "N2",
    "lesson": 22,
    "pattern": "〜にきまっている",
    "body": "意味： ⇒ 絶対に〜だと思う。\n① あの子の言うことなんかうそにきまっているよ。\n② 勝手にお父さんの車を使ったりしたら、しかられるにきまっている。\n③ こんな派手な色のお菓子、体に悪いにきまっています。\n接续： 普通形（ナ形・名）＋にきまっている\n注意： 说明：和「〜に違いない」不同，是主观、直觉地表达“无论谁都会这样认为”。",
    "questions": [
      {
        "q": "1",
        "stem": "兄が選んだ女性なんだから、絶対に（　）にきまっている。",
        "opts": [
          [
            "a",
            "すてき"
          ],
          [
            "b",
            "すてきの"
          ],
          [
            "c",
            "すてきな"
          ]
        ]
      },
      {
        "q": "2",
        "stem": "こんなにたくさんの仕事、1日では（　）にきまっている。",
        "opts": [
          [
            "a",
            "できないかもしれない"
          ],
          [
            "b",
            "できそうもない"
          ],
          [
            "c",
            "できない"
          ]
        ]
      }
    ]
  },
  "n2-l23-g01": {
    "level": "N2",
    "lesson": 23,
    "pattern": "〜ものだ（→24課-3、26課-2）",
    "body": "意味： ⇒ 一般的に見て、本来〜だ・〜というのは真理だ。\n① 自分では気がつきにくいが、どんな人にもくせがあるものだ。译：虽然自己很难察觉，但无论是谁都有习惯毛病。\n② 人間というのは本来一人では生きられないものだ。译：人本来就无法一个人生存。\n③ 彼は大会社の社長なのだそうだ。そうは見えなかった。人は外見だけではわからないものだ。译：据说他是一家大公司的社长。真看不出来啊。人不能只看外表。\n接续： 動辞書形/ない形・イ形い・ナ形な＋ものだ。说明：不用过去式。主语不是个别事物，而是统称性事物（人間・親・世の中等）。",
    "questions": [
      {
        "q": "1",
        "stem": "親は子供の面倒をちゃんと（　）ものだ。 a 見る　b 見ている　c 見た",
        "opts": []
      },
      {
        "q": "2",
        "stem": "（　）は、借りたらすぐ返すものだ。 a 1,000円　b お金　c あの時のお金",
        "opts": []
      },
      {
        "q": "3",
        "stem": "（　）ときは、前日よく休むものです。 a 山登りをする　b 今度の連休に富士山に登る　c A社のツアーで富士山に登る",
        "opts": []
      },
      {
        "q": "4",
        "stem": "人にはさみを渡すときは、とがったほうを相手に向ける（　）。 a ものです　b ものではありません　c ものですか",
        "opts": []
      }
    ]
  },
  "n2-l23-g02": {
    "level": "N2",
    "lesson": 23,
    "pattern": "〜というものだ",
    "body": "意味： ⇒ 常識的に見て、まさに〜だ。\n① 今日中にアメリカまで荷物を届けろと言われても、それは無理というものだ。译：即使让我今天之内把行李寄送到美国，那也是难以办到的啊。\n② 他人の物を断りもなく使うなんて、あつかましいというものだ。译：未经允许就用别人的东西，真是厚颜无耻。\n③ 出版した本の評判がいいそうだ。苦労したかいがあったというものだ。译：据说出版的书获得了好评。真是没有白辛苦啊。\n接续： 普通形（ナ形だ・名だ）＋というものだ",
    "questions": [
      {
        "q": "1",
        "stem": "1か月夏休みがあればいいなあと思うが、それは普通の会社員には（　）というものだ。 a ぜいたく　b うれしい　c うらやましい",
        "opts": []
      },
      {
        "q": "2",
        "stem": "彼は仕事を辞めて妻の看病をするという。これこそ（　）というものだ。 a 夫　b 忙しい　c 真の愛情",
        "opts": []
      }
    ]
  },
  "n2-l23-g03": {
    "level": "N2",
    "lesson": 23,
    "pattern": "〜にすぎない",
    "body": "意味： ⇒ ただ〜だけで、それ以上ではない。\n① 調査では、お米を全く食べないと答えた人は1.2%にすぎなかった。译：据调查，回答说完全不吃大米的人只不过是1.2%而已。\n② 一社員にすぎないわたしに、会社の経営のことなど決められない。译：我只不过是一名普通员工，不能决定公司的经营问题。\n③ お礼なんてとんでもない。わたしは当たり前のことをしたにすぎません。译：不用感谢我。我只不过做了应该做的事而已。\n接续： 名・普通形（ナ形/名：〜である）＋にすぎない。",
    "questions": [
      {
        "q": "1",
        "stem": "この作曲家はほとんど無名である。この作品だけが（　）にすぎない。 a 有名　b 有名だ　c 有名である",
        "opts": []
      },
      {
        "q": "2",
        "stem": "わたしが知っているフランス語は、（　）程度にすぎない。 a あいさつができる　b 論文が書ける　c 新聞が読める",
        "opts": []
      },
      {
        "q": "3",
        "stem": "大統領も一人の人間にすぎないのだから、（　）はずだ。 a 重要な命令ができる　b いろいろ悩むこともある　c 世界各国の人と会う機会が多い",
        "opts": []
      },
      {
        "q": "4",
        "stem": "漫画をかくことはわたしの（　）であるにすぎず、専門に勉強したわけではない。 a 目的　b 仕事　c 趣味",
        "opts": []
      }
    ]
  },
  "n2-l23-g04": {
    "level": "N2",
    "lesson": 23,
    "pattern": "〜にほかならない",
    "body": "意味： ⇒ 〜だ。それ以外ではない。〔硬い言い方〕译：就是……，除此以外并非其他。\n① 将来この国を支えるのは、若い君たちにほかなりません。译：将来支撑这个国家的正是年轻的你们。\n② 人間も自然の一部にほかならないということを忘れてはならない。译：我们不能忘记人类也正是自然界的一部分。\n③ このような証言ができるのは、本人が実際に犯行現場にいたからにほかならない。译：之所以能够提供这样的证言，正是因为本人当时在犯罪现场。\n接续： 名＋にほかならない。说明：表示说话人的断定性判断。也有前接「普通形＋から」的例子，如例③。",
    "questions": [
      {
        "q": "1",
        "stem": "外来語も日本語の（　）にほかならない。元の語とは意味や使い方が異なるのだ。 a 一部　b 一部だ　c 一部である",
        "opts": []
      },
      {
        "q": "2",
        "stem": "ご両親が厳しいことを言うのは、あなたのことを（　）にほかならない。 a 心配している　b 心配しているから　c 心配しているからだ",
        "opts": []
      },
      {
        "q": "3",
        "stem": "文章を書くことは（　）にほかならない。 a 楽しい　b 難しくないの　c 考えること",
        "opts": []
      }
    ]
  },
  "n2-l23-g05": {
    "level": "N2",
    "lesson": 23,
    "pattern": "〜に越したことはない",
    "body": "意味： ⇒ 当然のことだが〜ほうがいい。\n① 値段に関係なく質のいいものを買いたいが、安く買えるに越したことはない。译：虽然不考虑价格也想买质量好的东西，但能买得便宜些最好。\n② 旅行の荷物は軽いに越したことはない。译：旅行的行李最好轻便。\n③ ふだん使う道具の使い方は簡単であるに越したことはない。译：平时用的工具，使用方法最好简单些。\n接续： 普通形現在（ナ形/名：〜である）＋に越したことはない。",
    "questions": [
      {
        "q": "1",
        "stem": "けんかなど（　）に越したことはないが、けんかして初めてわかりあえることもある。 a しない　b しないこと　c しないの",
        "opts": []
      },
      {
        "q": "2",
        "stem": "人間は外見ではなく中身だとは思うが、もちろん外見が（　）に越したことはない。 a 関係ない　b 悪い　c いい",
        "opts": []
      },
      {
        "q": "3",
        "stem": "人によって好みは違うから、客にとって商品の選択肢は（　）に越したことはないだろう。 a 少ない　b 多い　c ある",
        "opts": []
      },
      {
        "q": "4",
        "stem": "（　）に越したことはないだろうが、失敗を恐れていては何もできない。 a 失敗から学ぶ　b 失敗はしない　c 失敗がある",
        "opts": []
      }
    ]
  },
  "n2-l23-g06": {
    "level": "N2",
    "lesson": 23,
    "pattern": "〜しかない・〜よりほかない",
    "body": "意味： ⇒ 〜以外に選択肢・可能性・方法がない。\n① この道は一方通行だから、戻りたくてもまっすぐ行くしかない。译：因为这条路是单行线，所以即使想返回也只能向前直行。\n② 会議で企画の中止が決まったなら、この決定を受け入れるよりほかないでしょう。译：如果会议上已经决定中止项目计划，就只好接受这个决定了吧。\n③ ずっと欲しかったかばんがセールで半額になっている。これは買うしかない。译：一直想要的包变成半价促销了。只能买了。\n接续： 動辞書形＋しかない・よりほかない。说明：表示说话人“因为没有其他选择余地，只好选择这个选项”的心情。",
    "questions": [
      {
        "q": "1",
        "stem": "家を買うには銀行からお金を（　）よりほかない。 a 借りる　b 借りた　c 借りられる",
        "opts": []
      },
      {
        "q": "2",
        "stem": "今年は夏休みもずっと忙しかったから、旅行は（　）よりほかなかった。 a あきらめる　b あきらめない　c しない",
        "opts": []
      },
      {
        "q": "3",
        "stem": "もう後には引き返せない。ここまできたら（　）しかない。 a もう止める　b 前に進む　c 戻る",
        "opts": []
      }
    ]
  },
  "n2-l23-g07": {
    "level": "N2",
    "lesson": 23,
    "pattern": "〜べきだ／〜べきではない",
    "body": "意味： ⇒ 〜するのが当然だ・〜しなければならない・〜したほうがいい／〜してはいけない。\n① 今日できることは明日に延ばさず今日するべきだ。译：今天能做的事情不要推到明天，应该今天就做。\n② もう会えないなら、彼の連絡先を聞いておくべきだった。译：如果再也见不到他，应该事先问问他的联系方式。\n③ すべての国民の幸せを目指すのが、政治の本来あるべき姿である。译：实现所有国民的幸福，这是政治原本应有的状态。\n④ そんな質問は、初めて会った人にすべきではない。译：不应该对初次见面的人问那样的问题。\n接续： 動辞書形＋べきだ・べきではない。例外：する→するべき/すべき；名詞接続：べき・べきではない＋名。说明：叙述说话人的主张。不用于规则规定的事情。",
    "questions": [
      {
        "q": "1",
        "stem": "子供はできるだけたくさん外で（　）べきです。 a 遊ばせ　b 遊ばせている　c 遊ばせる",
        "opts": []
      },
      {
        "q": "2",
        "stem": "目上の人にそんな失礼なことを（　）。 a 言うべきではない　b 言わないべきだ　c 言わぬべきだ",
        "opts": []
      },
      {
        "q": "3",
        "stem": "大学に入るには入学試験に（　）。 a 合格したほうがいい　b 合格するべきだ　c 合格しなければならない",
        "opts": []
      }
    ]
  },
  "n2-l24-g01": {
    "level": "N2",
    "lesson": 24,
    "pattern": "〜（よ）うではないか",
    "body": "意味： ⇒ 一緒に〜しよう・〜しませんか。〔硬い言い方〕译：一起做……吧；不是一起做……吗？书面语。\n① 環境を守るために何ができるか、考えてみようではないか。译：让我们一起来思考一下为了保护环境能做些什么吧。\n② みんなで協力して、このイベントを成功させようじゃないか。译：大家一起协力把这个活动办成功吧。\n③ 問題の解決を目指し、話し合おうではありませんか。译：为了解决问题，我们好好商量一下吧。\n接续： 動う・よう形＋ではないか。说明：强烈邀请的男性化说法，常见于政治家演说等。日常会话中不常用。",
    "questions": [
      {
        "q": "1",
        "stem": "これからわたしたちの力で、明るい日本を（　）ではありませんか。 a 作っていこう　b 作っていく　c 作っていくの",
        "opts": []
      },
      {
        "q": "2",
        "stem": "皆さん、リサイクル運動に（　）。 a 協力しようではない　b 協力しようではないのか　c 協力しようではないか",
        "opts": []
      }
    ]
  }
}